portainer_ce_api/__init__.py
portainer_ce_api/api_client.py
portainer_ce_api/configuration.py
portainer_ce_api/rest.py
portainer_ce_api/api/__init__.py
portainer_ce_api/api/auth_api.py
portainer_ce_api/api/backup_api.py
portainer_ce_api/api/custom_templates_api.py
portainer_ce_api/api/default_api.py
portainer_ce_api/api/dockerhub_api.py
portainer_ce_api/api/edge_api.py
portainer_ce_api/api/edge_groups_api.py
portainer_ce_api/api/edge_jobs_api.py
portainer_ce_api/api/edge_stacks_api.py
portainer_ce_api/api/edge_templates_api.py
portainer_ce_api/api/endpoint_groups_api.py
portainer_ce_api/api/endpoints_api.py
portainer_ce_api/api/motd_api.py
portainer_ce_api/api/registries_api.py
portainer_ce_api/api/resource_controls_api.py
portainer_ce_api/api/roles_api.py
portainer_ce_api/api/settings_api.py
portainer_ce_api/api/stacks_api.py
portainer_ce_api/api/status_api.py
portainer_ce_api/api/tags_api.py
portainer_ce_api/api/team_memberships_api.py
portainer_ce_api/api/teams_api.py
portainer_ce_api/api/templates_api.py
portainer_ce_api/api/upload_api.py
portainer_ce_api/api/users_api.py
portainer_ce_api/api/webhooks_api.py
portainer_ce_api/api/websocket_api.py
portainer_ce_api/models/__init__.py
portainer_ce_api/models/auth_authenticate_payload.py
portainer_ce_api/models/auth_authenticate_response.py
portainer_ce_api/models/auth_oauth_payload.py
portainer_ce_api/models/customtemplates_custom_template_from_file_content_payload.py
portainer_ce_api/models/customtemplates_custom_template_from_git_repository_payload.py
portainer_ce_api/models/customtemplates_custom_template_update_payload.py
portainer_ce_api/models/customtemplates_file_response.py
portainer_ce_api/models/dockerhub_dockerhub_update_payload.py
portainer_ce_api/models/edgegroups_edge_group_create_payload.py
portainer_ce_api/models/edgegroups_edge_group_update_payload.py
portainer_ce_api/models/edgejobs_edge_job_create_from_file_content_payload.py
portainer_ce_api/models/edgejobs_edge_job_create_from_file_payload.py
portainer_ce_api-2.6.1.dist-info/METADATA
portainer_ce_api-2.6.1.dist-info/WHEEL
portainer_ce_api-2.6.1.dist-info/top_level.txt
portainer_ce_api-2.6.1.dist-info/RECORD
