Metadata-Version: 2.1
Name: portainer-ce-api
Version: 2.6.1
Summary: PortainerCE API
Home-page: https://github.com/SirumTME/portainer_ce_api
Author-email: info@portainer.io
License: UNKNOWN
Keywords: Swagger,PortainerCE API
Platform: UNKNOWN
Requires-Dist: certifi (>=2017.4.17)
Requires-Dist: python-dateutil (>=2.1)
Requires-Dist: six (>=1.10)
Requires-Dist: urllib3 (>=1.23)
